django_custom_indexes/__init__.py
django_custom_indexes/model_fields.py
django_custom_indexes/backends/__init__.py
django_custom_indexes/backends/postgresql_psycopg2/__init__.py
django_custom_indexes/backends/postgresql_psycopg2/base.py
django_custom_indexes/backends/postgresql_psycopg2/schema.py
django_custom_indexes-0.1.5.dist-info/DESCRIPTION.rst
django_custom_indexes-0.1.5.dist-info/METADATA
django_custom_indexes-0.1.5.dist-info/RECORD
django_custom_indexes-0.1.5.dist-info/WHEEL
django_custom_indexes-0.1.5.dist-info/metadata.json
django_custom_indexes-0.1.5.dist-info/top_level.txt
