Metadata-Version: 2.0
Name: django-custom-indexes
Version: 0.1.5
Summary: PostgreSQL custom indexes for Django models
Home-page: https://github.com/joshtechnologygroup/django-custom-indexes/
Author: Anshul Chhangani
Author-email: anshul.chhangani@gmail.com
License: BSD
Platform: UNKNOWN
Classifier: Environment :: Web Environment
Classifier: Framework :: Django :: 1.7
Classifier: Framework :: Django :: 1.8
Classifier: Framework :: Django :: 1.9
Classifier: Framework :: Django :: 1.10
Classifier: Framework :: Django :: 1.11
Classifier: Intended Audience :: Developers
Classifier: License :: OSI Approved :: BSD License
Classifier: Operating System :: OS Independent
Classifier: Programming Language :: Python :: 2.7
Classifier: Topic :: Database
Classifier: Topic :: Internet :: WWW/HTTP
